<?xml version="1.0"?>
<!DOCTYPE hibernate-mapping PUBLIC "-//Hibernate/Hibernate Mapping DTD 3.0//EN" "http://hibernate.sourceforge.net/hibernate-mapping-3.0.dtd">

<hibernate-mapping>
	<class name="com.cloud.bridge.model.SObjectItem" table="sobject_item"  lazy="true">
   		<id name="id" type="long" column="ID" >
   			<generator class="native" />
  		</id>

  		<property name="version">
     		<column name="Version" />
  		</property>
  		
  		<property name="md5">
     		<column name="MD5" />
  		</property>
  		
  		<property name="storedPath">
     		<column name="StoredPath" />
  		</property>
  		
  		<property name="storedSize">
     		<column name="StoredSize" />
  		</property>
  		
  		<property name="createTime" type="com.cloud.bridge.persist.GMTDateTimeUserType">
     		<column name="CreateTime" />
  		</property>
  		
  		<property name="lastModifiedTime" type="com.cloud.bridge.persist.GMTDateTimeUserType">
     		<column name="LastModifiedTime" />
  		</property>
  		
  		<property name="lastAccessTime" type="com.cloud.bridge.persist.GMTDateTimeUserType">
     		<column name="LastAccessTime" />
  		</property>
  		
  		<many-to-one name="theObject" column="SObjectID" 
  			class="com.cloud.bridge.model.SObject"
  			cascade="none" 
  		/>
 	</class>
</hibernate-mapping>

